bigcode_fetcher/__init__.py
bigcode_fetcher/cli.py
bigcode_fetcher/constants.py
bigcode_fetcher/downloader.py
bigcode_fetcher/fetcher.py
bigcode_fetcher/project.py
bigcode_fetcher-0.1.2.data/scripts/bigcode-fetcher
bigcode_fetcher-0.1.2.dist-info/DESCRIPTION.rst
bigcode_fetcher-0.1.2.dist-info/METADATA
bigcode_fetcher-0.1.2.dist-info/RECORD
bigcode_fetcher-0.1.2.dist-info/WHEEL
bigcode_fetcher-0.1.2.dist-info/metadata.json
bigcode_fetcher-0.1.2.dist-info/top_level.txt
bigcode_fetcher-0.1.2.dist-info/zip-safe
tests/fixtures/__init__.py
