Metadata-Version: 2.0
Name: bigcode-fetcher
Version: 0.1.2
Summary: Tool to search and fetch code from GitHub
Home-page: https://github.com/tuvistavie/bigcode-tools/tree/master/code-fetcher
Author: Daniel Perez
Author-email: tuvistavie@gmail.com
License: UNKNOWN
Download-URL: https://github.com/tuvistavie/bigcode-tools/archive/master.zip
Platform: UNKNOWN
Classifier: Development Status :: 4 - Beta
Classifier: Intended Audience :: Developers
Classifier: License :: OSI Approved :: MIT License
Classifier: Operating System :: OS Independent
Classifier: Programming Language :: Python :: 3
Requires-Dist: requests
Requires-Dist: grequests
Provides-Extra: test
Requires-Dist: nose; extra == 'test'
Requires-Dist: requests-mock; extra == 'test'
